{
  "timestamp": "2025-12-08T14:27:25.780562",
  "forecast_days": 7,
  "best_window_start_utc": "2025-12-13 02:00:00+00:00",
  "estimated_avg_gwei": -0.1990015955738479,
  "model_accuracy": {
    "mae": 0.27906263567579204,
    "mae_std": 0.09737754236416615,
    "rmse": 0.4635146668678131,
    "rmse_std": 0.24202945482705465,
    "mape": 276.3602910339794,
    "mape_std": 154.34558972533637,
    "r_squared": -1.998250162679577,
    "r_squared_std": 2.0867823213805163,
    "validation_method": "cross_validation",
    "n_folds": 5
  },
  "model_fit_metrics": {
    "aic_full": 515.3284115196085,
    "bic_full": 555.4534560697116,
    "log_likelihood_full": -248.66420575980425
  },
  "forecast_csv": "data/pillar2_gas/forecast/gas_forecast_7d_20251208.csv"
}